pyrepseq/__init__.py
pyrepseq/clustering.py
pyrepseq/distance.py
pyrepseq/entropy.py
pyrepseq/io.py
pyrepseq/nn.py
pyrepseq/plotting.py
pyrepseq/stats.py
pyrepseq/util.py
pyrepseq/version.py
pyrepseq/data/pcdelta_pbmc_minervina.csv
pyrepseq/data/vdists_alpha.csv
pyrepseq/data/vdists_beta.csv
pyrepseq/metric/__init__.py
pyrepseq/metric/levenshtein.py
pyrepseq/metric/metric.py
pyrepseq/metric/tcr_metric/__init__.py
pyrepseq/metric/tcr_metric/tcr_levenshtein.py
pyrepseq/metric/tcr_metric/tcr_metric.py
pyrepseq/metric/tcr_metric/tcrdist/__init__.py
pyrepseq/metric/tcr_metric/tcrdist/simplified_tcrdist_interface.py
pyrepseq/metric/tcr_metric/tcrdist/tcrdist_metric.py
pyrepseq-1.5.2.dist-info/licenses/LICENSE
pyrepseq-1.5.2.dist-info/METADATA
pyrepseq-1.5.2.dist-info/WHEEL
pyrepseq-1.5.2.dist-info/top_level.txt
pyrepseq-1.5.2.dist-info/RECORD
