Metadata-Version: 2.4
Name: pyrepseq
Version: 1.5.2
Summary: Python library for immune repertoire analyses
Home-page: http://pyrepseq.readthedocs.io/
Download-URL: http://github.com/andim/pyrepseq
Author: Q-Immuno Lab (PI: Andreas Tiffeau-Mayer)
Author-email: qimmuno@gmail.com
Maintainer: Andreas Tiffeau-Mayer
Maintainer-email: andimscience@gmail.com
License: MIT
Platform: OS Independent
Classifier: Development Status :: 5 - Production/Stable
Classifier: Environment :: Console
Classifier: Intended Audience :: Science/Research
Classifier: License :: OSI Approved :: MIT License
Classifier: Operating System :: OS Independent
Classifier: Programming Language :: Python :: 3
Classifier: Programming Language :: Python :: 3.8
Classifier: Topic :: Scientific/Engineering
License-File: LICENSE
Requires-Dist: numpy
Requires-Dist: scipy
Requires-Dist: pandas
Requires-Dist: rapidfuzz
Requires-Dist: Levenshtein
Requires-Dist: matplotlib
Requires-Dist: seaborn
Requires-Dist: igraph
Requires-Dist: scikit-learn
Requires-Dist: logomaker
Requires-Dist: biopython
Requires-Dist: tidytcells~=2.0
Requires-Dist: tqdm
Provides-Extra: dev
Requires-Dist: pytest; extra == "dev"
Requires-Dist: pytest-cov; extra == "dev"
Requires-Dist: sphinx; extra == "dev"
Requires-Dist: sphinx-rtd-theme; extra == "dev"
Provides-Extra: full
Requires-Dist: tcrdist3; extra == "full"
Requires-Dist: pwseqdist; extra == "full"
Dynamic: author
Dynamic: author-email
Dynamic: classifier
Dynamic: description
Dynamic: description-content-type
Dynamic: download-url
Dynamic: home-page
Dynamic: license
Dynamic: license-file
Dynamic: maintainer
Dynamic: maintainer-email
Dynamic: platform
Dynamic: provides-extra
Dynamic: requires-dist
Dynamic: summary
